apache_beam/__init__.py
apache_beam/error.py
apache_beam/pipeline.py
apache_beam/pipeline_test.py
apache_beam/pvalue.py
apache_beam/pvalue_test.py
apache_beam/version.py
apache_beam/coders/__init__.py
apache_beam/coders/avro_record.py
apache_beam/coders/coder_impl.pxd
apache_beam/coders/coder_impl.py
apache_beam/coders/coder_impl_row_encoders.pyx
apache_beam/coders/coders.py
apache_beam/coders/coders_property_based_test.py
apache_beam/coders/coders_test.py
apache_beam/coders/coders_test_common.py
apache_beam/coders/fast_coders_test.py
apache_beam/coders/observable.py
apache_beam/coders/observable_test.py
apache_beam/coders/proto2_coder_test_messages_pb2.py
apache_beam/coders/row_coder.py
apache_beam/coders/row_coder_test.py
apache_beam/coders/slow_coders_test.py
apache_beam/coders/slow_stream.py
apache_beam/coders/standard_coders_test.py
apache_beam/coders/stream.pxd
apache_beam/coders/stream.pyx
apache_beam/coders/stream_test.py
apache_beam/coders/typecoders.py
apache_beam/coders/typecoders_test.py
apache_beam/dataframe/__init__.py
apache_beam/dataframe/convert.py
apache_beam/dataframe/convert_test.py
apache_beam/dataframe/doctests.py
apache_beam/dataframe/doctests_test.py
apache_beam/dataframe/expressions.py
apache_beam/dataframe/expressions_test.py
apache_beam/dataframe/frame_base.py
apache_beam/dataframe/frame_base_test.py
apache_beam/dataframe/frames.py
apache_beam/dataframe/frames_test.py
apache_beam/dataframe/io.py
apache_beam/dataframe/io_it_test.py
apache_beam/dataframe/io_test.py
apache_beam/dataframe/pandas_docs_test.py
apache_beam/dataframe/pandas_doctests_test.py
apache_beam/dataframe/pandas_top_level_functions.py
apache_beam/dataframe/partitionings.py
apache_beam/dataframe/partitionings_test.py
apache_beam/dataframe/schemas.py
apache_beam/dataframe/schemas_test.py
apache_beam/dataframe/transforms.py
apache_beam/dataframe/transforms_test.py
apache_beam/examples/__init__.py
apache_beam/examples/avro_bitcoin.py
apache_beam/examples/fastavro_it_test.py
apache_beam_ai2-2.47.0.dist-info/METADATA
apache_beam_ai2-2.47.0.dist-info/WHEEL
apache_beam_ai2-2.47.0.dist-info/top_level.txt
apache_beam_ai2-2.47.0.dist-info/RECORD
